crypto_treehole/__init__.py
crypto_treehole/crypto_treehole.py
crypto_treehole-0.2.5.dist-info/LICENSE
crypto_treehole-0.2.5.dist-info/METADATA
crypto_treehole-0.2.5.dist-info/WHEEL
crypto_treehole-0.2.5.dist-info/top_level.txt
crypto_treehole-0.2.5.dist-info/RECORD
