Metadata-Version: 2.1
Name: crypto-treehole
Version: 0.2.5
Summary: a treehole bot server for mixin messenger and rum system (both crypto products)
Home-page: https://github.com/liujuanjuan1984/crypto_treehole
Author: liujuanjuan1984
Author-email: qiaoanlu@163.com
Project-URL: Github Repo, https://github.com/liujuanjuan1984/crypto_treehole
Project-URL: Bug Tracker, https://github.com/liujuanjuan1984/crypto_treehole/issues
Project-URL: About Quorum, https://github.com/rumsystem/quorum
Project-URL: About Mixin, https://github.com/MixinNetwork/mixin
Keywords: rumsystem,quorum,treehole,mixin
Classifier: Programming Language :: Python :: 3
Classifier: Programming Language :: Python :: 3.8
Classifier: License :: OSI Approved :: MIT License
Classifier: Operating System :: OS Independent
Requires-Python: >=3.8
License-File: LICENSE
Requires-Dist: requests
Requires-Dist: mixinsdk ==0.2.1
Requires-Dist: quorum-mininode-py >=1.2.1
Requires-Dist: quorum-data-py >=1.1.5
